simulated_annealing_variants/README.md
simulated_annealing_variants/__init__.py
simulated_annealing_variants/simulated_annealing.py
simulated_annealing_variants/simulated_annealing_jax.py
simulated_annealing_variants/simulated_annealing_qrf.py
simulated_annealing_variants/simulated_annealing_rf.py
simulated_annealing_variants/temperature.py
simulated_annealing_variants/utils.py
simulated_annealing_variants-1.1.8.dist-info/METADATA
simulated_annealing_variants-1.1.8.dist-info/WHEEL
simulated_annealing_variants-1.1.8.dist-info/licenses/LICENSE
simulated_annealing_variants-1.1.8.dist-info/RECORD
