Metadata-Version: 2.3
Name: simulated-annealing-variants
Version: 1.1.8
Summary: Python implementations of simulated annealing variants such as quasi rejection-free and rejection-free simulated annealing to optimize QUBO problems.
Project-URL: Homepage, https://github.com/MichelKrispin/rf-simulated-annealing
Author-email: Michel Krispin <michel.krispin@tuhh.de>
License-Expression: MIT
License-File: LICENSE
Classifier: Programming Language :: Python :: 3
Requires-Python: >=3.7
Requires-Dist: numpy~=1.26
